pydoge_ds/SQLEngine.py
pydoge_ds/__init__.py
pydoge_ds/helpers.py
PyDoge_ds-0.1.1.dist-info/LICENSE
PyDoge_ds-0.1.1.dist-info/METADATA
PyDoge_ds-0.1.1.dist-info/WHEEL
PyDoge_ds-0.1.1.dist-info/top_level.txt
PyDoge_ds-0.1.1.dist-info/RECORD
